<?xml version="1.0" encoding="utf-8"?>
<kup encoding="utf-16" ramOffset="00" optimizeStrings="true">
	<pointerTables />
	<stringBounds />
	<entries>
		<entry name="001" offset="00" relocatable="true" max_length="0">
			<original>&#xE;&#x3;#&#x0;Hey&#xE;&#x7;&#x0;&#x4;&#x8;&#x0;&#x0;&#x0;.&#xE;&#x7;&#x0;&#x4;&#x8;&#x0;&#x0;&#x0;.&#xE;&#x7;&#x0;&#x4;&#x8;&#x0;&#x0;&#x0;.&#xE;&#x7;&#x0;&#x4;&#x14;&#x0;&#x0;&#x0; So I just thought of a super-
awesome nickname for you!&#xE;&#x3;&#x17;&#x0; Wanna
hear it?&#xE;&#xF;&#x5;&#x4;&#x15;&#x0;(&#x0;
What is it?
I'm good.</original>
			<edited>&#xE;&#x3;#&#x0;Hey&#xE;&#x7;&#x0;&#x4;&#x8;&#x0;&#x0;&#x0;.&#xE;&#x7;&#x0;&#x4;&#x8;&#x0;&#x0;&#x0;.&#xE;&#x7;&#x0;&#x4;&#x8;&#x0;&#x0;&#x0;.&#xE;&#x7;&#x0;&#x4;&#x14;&#x0;&#x0;&#x0; So I just thought of a super-
awesome nickname for you!&#xE;&#x3;&#x17;&#x0; Wanna
hear it?&#xE;&#xF;&#x5;&#x4;&#x15;&#x0;(&#x0;
What is it?
I'm good.</edited>
			<subEntries />
		</entry>
		<entry name="002" offset="00" relocatable="true" max_length="0">
			<original>&#xE;&#x3;	&#x0;What?!&#xE;&#x7;&#x0;&#x4;&#x14;&#x0;&#x0;&#x0; You don't wanna hear it?&#xE;&#x7;&#x0;&#x4;(&#x0;&#x0;&#x0;
&#xE;&#x3;&#x1B;&#x0;Dude, try and live a little! Have
some fun with it,&#xE;&#x7;&#x0;&#x4;&#x14;&#x0;&#x0;&#x0; &#xE;&#x5;&#x8;&#x0;!</original>
			<edited>&#xE;&#x3;	&#x0;What?!&#xE;&#x7;&#x0;&#x4;&#x14;&#x0;&#x0;&#x0; You don't wanna hear it?&#xE;&#x7;&#x0;&#x4;(&#x0;&#x0;&#x0;
&#xE;&#x3;&#x1B;&#x0;Dude, try and live a little! Have
some fun with it,&#xE;&#x7;&#x0;&#x4;&#x14;&#x0;&#x0;&#x0; &#xE;&#x5;&#x8;&#x0;!</edited>
			<subEntries />
		</entry>
		<entry name="003" offset="00" relocatable="true" max_length="0">
			<original>&#xE;&#x3;&amp;&#x0;OK! You ready?&#xE;&#x7;&#x0;&#x4;&#x14;&#x0;&#x0;&#x0; It's "&#xE;&#x5;&#x8;&#x0;"!&#xE;&#x7;&#x0;&#x4;(&#x0;&#x0;&#x0;
&#xE;&#x3;&#x0;&#x0;Cool, right?&#xE;&#xF;&#x5;&#x4;&#x15;&#x0;(&#x0;
I like it!
I hate it!</original>
			<edited>&#xE;&#x3;&amp;&#x0;OK! You ready?&#xE;&#x7;&#x0;&#x4;&#x14;&#x0;&#x0;&#x0; It's "&#xE;&#x5;&#x8;&#x0;"!&#xE;&#x7;&#x0;&#x4;(&#x0;&#x0;&#x0;
&#xE;&#x3;&#x0;&#x0;Cool, right?&#xE;&#xF;&#x5;&#x4;&#x15;&#x0;(&#x0;
I like it!
I hate it!</edited>
			<subEntries />
		</entry>
		<entry name="004" offset="00" relocatable="true" max_length="0">
			<original>&#xE;&#x3;!&#x0;Right?!&#xE;&#x7;&#x0;&#x4;(&#x0;&#x0;&#x0; When it came to me, I knew
I had to tell you!&#xE;&#x0;&#x4;&#x0;&#xE;&#x3;&#x5;&#x0;OK, from now on I'm calling you
&#xE;&#x5;&#x8;&#x0;!&#xE;&#x7;&#x0;&#x4;(&#x0;&#x0;&#x0; Later, &#xE;&#x7;&#x0;&#x4;&#x14;&#x0;&#x0;&#x0;&#xE;&#x5;&#x7;&#x0;!</original>
			<edited>&#xE;&#x3;!&#x0;Right?!&#xE;&#x7;&#x0;&#x4;(&#x0;&#x0;&#x0; When it came to me, I knew
I had to tell you!&#xE;&#x0;&#x4;&#x0;&#xE;&#x3;&#x5;&#x0;OK, from now on I'm calling you
&#xE;&#x5;&#x8;&#x0;!&#xE;&#x7;&#x0;&#x4;(&#x0;&#x0;&#x0; Later, &#xE;&#x7;&#x0;&#x4;&#x14;&#x0;&#x0;&#x0;&#xE;&#x5;&#x7;&#x0;!</edited>
			<subEntries />
		</entry>
		<entry name="005" offset="00" relocatable="true" max_length="0">
			<original>&#xE;&#x3;	&#x0;Wha...&#xE;&#x7;&#x0;&#x4;&#x8;&#x0;&#x0;&#x0; Really?&#xE;&#x7;&#x0;&#x4;(&#x0;&#x0;&#x0; &#xE;&#x3;
&#x0;Hmmm&#xE;&#x7;&#x0;&#x4;&#x8;&#x0;&#x0;&#x0;.&#xE;&#x7;&#x0;&#x4;&#x8;&#x0;&#x0;&#x0;.&#xE;&#x7;&#x0;&#x4;&#x8;&#x0;&#x0;&#x0;.&#xE;&#x7;&#x0;&#x4;&#x14;&#x0;&#x0;&#x0;&#xE;&#x0;&#x4;&#x0;&#xE;&#x3;&#x15;&#x0;OK,&#xE;&#x7;&#x0;&#x4;&#x8;&#x0;&#x0;&#x0; well, until I think of something
better, I'll just keep calling you
&#xE;&#x5;&#x8;&#x0;. &#xE;&#x7;&#x0;&#x4;&#x14;&#x0;&#x0;&#x0;&#xE;&#x3;%&#x0;&#xE;&#xE;&#x3;&#x0;&#xE;&#x5;&#x7;&#x0;!</original>
			<edited>&#xE;&#x3;	&#x0;Wha...&#xE;&#x7;&#x0;&#x4;&#x8;&#x0;&#x0;&#x0; Really?&#xE;&#x7;&#x0;&#x4;(&#x0;&#x0;&#x0; &#xE;&#x3;
&#x0;Hmmm&#xE;&#x7;&#x0;&#x4;&#x8;&#x0;&#x0;&#x0;.&#xE;&#x7;&#x0;&#x4;&#x8;&#x0;&#x0;&#x0;.&#xE;&#x7;&#x0;&#x4;&#x8;&#x0;&#x0;&#x0;.&#xE;&#x7;&#x0;&#x4;&#x14;&#x0;&#x0;&#x0;&#xE;&#x0;&#x4;&#x0;&#xE;&#x3;&#x15;&#x0;OK,&#xE;&#x7;&#x0;&#x4;&#x8;&#x0;&#x0;&#x0; well, until I think of something
better, I'll just keep calling you
&#xE;&#x5;&#x8;&#x0;. &#xE;&#x7;&#x0;&#x4;&#x14;&#x0;&#x0;&#x0;&#xE;&#x3;%&#x0;&#xE;&#xE;&#x3;&#x0;&#xE;&#x5;&#x7;&#x0;!</edited>
			<subEntries />
		</entry>
		<entry name="006" offset="00" relocatable="true" max_length="0">
			<original>&#xE;&#x3;	&#x0;Whaaat? &#xE;&#x7;&#x0;&#x4;&#x8;&#x0;&#x0;&#x0;Really?&#xE;&#x7;&#x0;&#x4;(&#x0;&#x0;&#x0; Well, OK. &#xE;&#x3;&#x17;&#x0;What do
you think would be good then?</original>
			<edited>&#xE;&#x3;	&#x0;Whaaat? &#xE;&#x7;&#x0;&#x4;&#x8;&#x0;&#x0;&#x0;Really?&#xE;&#x7;&#x0;&#x4;(&#x0;&#x0;&#x0; Well, OK. &#xE;&#x3;&#x17;&#x0;What do
you think would be good then?</edited>
			<subEntries />
		</entry>
		<entry name="007" offset="00" relocatable="true" max_length="0">
			<original>&#xE;&#x3;%&#x0;"&#xE;&#xE;&#x3;&#x0;&#xE;&#x5;&#x8;&#x0;"? Is that right?&#xE;&#xD;&#x8;&#x2;&#x2;Í&#xE;&#xF;&#x5;&#x4;&#x15;&#x0;(&#x0;
That's right!
That's wrong.</original>
			<edited>&#xE;&#x3;%&#x0;"&#xE;&#xE;&#x3;&#x0;&#xE;&#x5;&#x8;&#x0;"? Is that right?&#xE;&#xD;&#x8;&#x2;&#x2;Í&#xE;&#xF;&#x5;&#x4;&#x15;&#x0;(&#x0;
That's right!
That's wrong.</edited>
			<subEntries />
		</entry>
		<entry name="008" offset="00" relocatable="true" max_length="0">
			<original>&#xE;&#x3;&#xF;&#x0;Oh, did I hear you wrong?&#xE;&#x7;&#x0;&#x4;(&#x0;&#x0;&#x0; &#xE;&#x3;&#x0;&#x0;Sorry. 
Tell me again!</original>
			<edited>&#xE;&#x3;&#xF;&#x0;Oh, did I hear you wrong?&#xE;&#x7;&#x0;&#x4;(&#x0;&#x0;&#x0; &#xE;&#x3;&#x0;&#x0;Sorry. 
Tell me again!</edited>
			<subEntries />
		</entry>
		<entry name="009" offset="00" relocatable="true" max_length="0">
			<original>&#xE;&#x3;&#x16;&#x0;Hmm. &#xE;&#xE;&#x3;&#x0;&#xE;&#x5;&#x8;&#x0;, yeah? &#xE;&#x7;&#x0;&#x4;&#x8;&#x0;&#x0;&#x0;.&#xE;&#x7;&#x0;&#x4;&#x8;&#x0;&#x0;&#x0;.&#xE;&#x7;&#x0;&#x4;&#x8;&#x0;&#x0;&#x0;.&#xE;&#x7;&#x0;&#x4;(&#x0;&#x0;&#x0;&#xE;&#x3;%&#x0;Sounds
good!&#xE;&#x7;&#x0;&#x4;&#x14;&#x0;&#x0;&#x0; And it suits you somehow!&#xE;&#x0;&#x4;&#x0;&#xE;&#x3;&#x5;&#x0;Cool!&#xE;&#x7;&#x0;&#x4;&#x8;&#x0;&#x0;&#x0; I've got something new to call
you,&#xE;&#x7;&#x0;&#x4;&#x8;&#x0;&#x0;&#x0; &#xE;&#x5;&#x8;&#x0;! &#xE;&#x7;&#x0;&#x4;&#x14;&#x0;&#x0;&#x0;&#xE;&#xE;&#x3;&#x0;&#xE;&#x5;&#x7;&#x0;!</original>
			<edited>&#xE;&#x3;&#x16;&#x0;Hmm. &#xE;&#xE;&#x3;&#x0;&#xE;&#x5;&#x8;&#x0;, yeah? &#xE;&#x7;&#x0;&#x4;&#x8;&#x0;&#x0;&#x0;.&#xE;&#x7;&#x0;&#x4;&#x8;&#x0;&#x0;&#x0;.&#xE;&#x7;&#x0;&#x4;&#x8;&#x0;&#x0;&#x0;.&#xE;&#x7;&#x0;&#x4;(&#x0;&#x0;&#x0;&#xE;&#x3;%&#x0;Sounds
good!&#xE;&#x7;&#x0;&#x4;&#x14;&#x0;&#x0;&#x0; And it suits you somehow!&#xE;&#x0;&#x4;&#x0;&#xE;&#x3;&#x5;&#x0;Cool!&#xE;&#x7;&#x0;&#x4;&#x8;&#x0;&#x0;&#x0; I've got something new to call
you,&#xE;&#x7;&#x0;&#x4;&#x8;&#x0;&#x0;&#x0; &#xE;&#x5;&#x8;&#x0;! &#xE;&#x7;&#x0;&#x4;&#x14;&#x0;&#x0;&#x0;&#xE;&#xE;&#x3;&#x0;&#xE;&#x5;&#x7;&#x0;!</edited>
			<subEntries />
		</entry>
		<entry name="010" offset="00" relocatable="true" max_length="0">
			<original />
			<edited />
			<subEntries />
		</entry>
		<entry name="011" offset="00" relocatable="true" max_length="0">
			<original>&#xE;&#x3;&#x15;&#x0;Hey, so people have started calling
you &#xE;&#x11;&#x0;&#x2;&#x0;&#x0;, right?&#xE;&#x0;&#x4;&#x0;&#xE;&#x3;%&#x0;That's nice.&#xE;&#x7;&#x0;&#x4;&#x14;&#x0;&#x0;&#x0; It suits ya!&#xE;&#x7;&#x0;&#x4;(&#x0;&#x0;&#x0;&#xE;&#x0;&#x4;&#x0;&#xE;&#x3;&#x17;&#x0;Can I call you &#xE;&#x11;&#x0;&#x2;&#x0;&#x0; too?&#xE;&#xF;&#x5;&#x4;&#x15;&#x0;(&#x0;
Sure!
No way!</original>
			<edited>&#xE;&#x3;&#x15;&#x0;Hey, so people have started calling
you &#xE;&#x11;&#x0;&#x2;&#x0;&#x0;, right?&#xE;&#x0;&#x4;&#x0;&#xE;&#x3;%&#x0;That's nice.&#xE;&#x7;&#x0;&#x4;&#x14;&#x0;&#x0;&#x0; It suits ya!&#xE;&#x7;&#x0;&#x4;(&#x0;&#x0;&#x0;&#xE;&#x0;&#x4;&#x0;&#xE;&#x3;&#x17;&#x0;Can I call you &#xE;&#x11;&#x0;&#x2;&#x0;&#x0; too?&#xE;&#xF;&#x5;&#x4;&#x15;&#x0;(&#x0;
Sure!
No way!</edited>
			<subEntries />
		</entry>
		<entry name="012" offset="00" relocatable="true" max_length="0">
			<original>&#xE;&#x3;&#x3;&#x0;Awesome!&#xE;&#x7;&#x0;&#x4;(&#x0;&#x0;&#x0; Well, &#xE;&#x7;&#x0;&#x4;&#x8;&#x0;&#x0;&#x0;might as well get
started!&#xE;&#x3;%&#x0; Thanks, &#xE;&#x5;&#x8;&#x0;! Thanks
a bunch! &#xE;&#xE;&#x3;&#x0;&#xE;&#x7;&#x0;&#x4;&#x14;&#x0;&#x0;&#x0;&#xE;&#x5;&#x7;&#x0;!</original>
			<edited>&#xE;&#x3;&#x3;&#x0;Awesome!&#xE;&#x7;&#x0;&#x4;(&#x0;&#x0;&#x0; Well, &#xE;&#x7;&#x0;&#x4;&#x8;&#x0;&#x0;&#x0;might as well get
started!&#xE;&#x3;%&#x0; Thanks, &#xE;&#x5;&#x8;&#x0;! Thanks
a bunch! &#xE;&#xE;&#x3;&#x0;&#xE;&#x7;&#x0;&#x4;&#x14;&#x0;&#x0;&#x0;&#xE;&#x5;&#x7;&#x0;!</edited>
			<subEntries />
		</entry>
		<entry name="013" offset="00" relocatable="true" max_length="0">
			<original>&#xE;&#x3;&#x1B;&#x0;What?&#xE;&#x7;&#x0;&#x4;&#x14;&#x0;&#x0;&#x0; Why?&#xE;&#x7;&#x0;&#x4;&#x14;&#x0;&#x0;&#x0; Hey, don't get all
embarrassed about it&#xE;&#x7;&#x0;&#x4;&#x8;&#x0;&#x0;&#x0;.&#xE;&#x7;&#x0;&#x4;&#x8;&#x0;&#x0;&#x0;.&#xE;&#x7;&#x0;&#x4;&#x8;&#x0;&#x0;&#x0;.&#xE;&#x7;&#x0;&#x4;&#x14;&#x0;&#x0;&#x0;&#xE;&#x0;&#x4;&#x0;&#xE;&#x3;$&#x0;Anyway, if I start calling you 
&#xE;&#x11;&#x0;&#x2;&#x0;&#x0; all of a sudden, it'll
probably ruffle some feathers!
&#xE;&#x3;&#x15;&#x0;Yeah, you're right.&#xE;&#x7;&#x0;&#x4;(&#x0;&#x0;&#x0; I'll just stick to
calling you &#xE;&#x5;&#x8;&#x0;! That's what
I'll do, &#xE;&#x7;&#x0;&#x4;&#x14;&#x0;&#x0;&#x0;&#xE;&#x5;&#x7;&#x0;!</original>
			<edited>&#xE;&#x3;&#x1B;&#x0;What?&#xE;&#x7;&#x0;&#x4;&#x14;&#x0;&#x0;&#x0; Why?&#xE;&#x7;&#x0;&#x4;&#x14;&#x0;&#x0;&#x0; Hey, don't get all
embarrassed about it&#xE;&#x7;&#x0;&#x4;&#x8;&#x0;&#x0;&#x0;.&#xE;&#x7;&#x0;&#x4;&#x8;&#x0;&#x0;&#x0;.&#xE;&#x7;&#x0;&#x4;&#x8;&#x0;&#x0;&#x0;.&#xE;&#x7;&#x0;&#x4;&#x14;&#x0;&#x0;&#x0;&#xE;&#x0;&#x4;&#x0;&#xE;&#x3;$&#x0;Anyway, if I start calling you 
&#xE;&#x11;&#x0;&#x2;&#x0;&#x0; all of a sudden, it'll
probably ruffle some feathers!
&#xE;&#x3;&#x15;&#x0;Yeah, you're right.&#xE;&#x7;&#x0;&#x4;(&#x0;&#x0;&#x0; I'll just stick to
calling you &#xE;&#x5;&#x8;&#x0;! That's what
I'll do, &#xE;&#x7;&#x0;&#x4;&#x14;&#x0;&#x0;&#x0;&#xE;&#x5;&#x7;&#x0;!</edited>
			<subEntries />
		</entry>
		<entry name="014" offset="00" relocatable="true" max_length="0">
			<original>&#xE;&#x3;	&#x0;Huh?&#xE;&#x7;&#x0;&#x4;&#x8;&#x0;&#x0;&#x0; How come?&#xE;&#x7;&#x0;&#x4;(&#x0;&#x0;&#x0; &#xE;&#x3;&#x17;&#x0;What should I call
you then?</original>
			<edited>&#xE;&#x3;	&#x0;Huh?&#xE;&#x7;&#x0;&#x4;&#x8;&#x0;&#x0;&#x0; How come?&#xE;&#x7;&#x0;&#x4;(&#x0;&#x0;&#x0; &#xE;&#x3;&#x17;&#x0;What should I call
you then?</edited>
			<subEntries />
		</entry>
		<entry name="015" offset="00" relocatable="true" max_length="0">
			<original>"&#xE;&#xE;&#x3;&#x0;&#xE;&#x5;&#x8;&#x0;."&#xE;&#x7;&#x0;&#x4;(&#x0;&#x0;&#x0; &#xE;&#x3;&#x17;&#x0;Is that right?&#xE;&#xD;&#x8;&#x2;&#x2;Í&#xE;&#xF;&#x5;&#x4;&#x15;&#x0;(&#x0;
Yep!
Nope!</original>
			<edited>"&#xE;&#xE;&#x3;&#x0;&#xE;&#x5;&#x8;&#x0;."&#xE;&#x7;&#x0;&#x4;(&#x0;&#x0;&#x0; &#xE;&#x3;&#x17;&#x0;Is that right?&#xE;&#xD;&#x8;&#x2;&#x2;Í&#xE;&#xF;&#x5;&#x4;&#x15;&#x0;(&#x0;
Yep!
Nope!</edited>
			<subEntries />
		</entry>
		<entry name="016" offset="00" relocatable="true" max_length="0">
			<original>&#xE;&#x3;&#xF;&#x0;Oh, &#xE;&#x7;&#x0;&#x4;&#x8;&#x0;&#x0;&#x0;I got it wrong?&#xE;&#x7;&#x0;&#x4;(&#x0;&#x0;&#x0;&#xE;&#x3;	&#x0; Sorry. Let me
hear it one more time!</original>
			<edited>&#xE;&#x3;&#xF;&#x0;Oh, &#xE;&#x7;&#x0;&#x4;&#x8;&#x0;&#x0;&#x0;I got it wrong?&#xE;&#x7;&#x0;&#x4;(&#x0;&#x0;&#x0;&#xE;&#x3;	&#x0; Sorry. Let me
hear it one more time!</edited>
			<subEntries />
		</entry>
		<entry name="017" offset="00" relocatable="true" max_length="0">
			<original>&#xE;&#x3;&amp;&#x0;All right! Got it!&#xE;&#x7;&#x0;&#x4;(&#x0;&#x0;&#x0; &#xE;&#x3;%&#x0;From now on, I'm
gonna call you &#xE;&#x5;&#x8;&#x0;!</original>
			<edited>&#xE;&#x3;&amp;&#x0;All right! Got it!&#xE;&#x7;&#x0;&#x4;(&#x0;&#x0;&#x0; &#xE;&#x3;%&#x0;From now on, I'm
gonna call you &#xE;&#x5;&#x8;&#x0;!</edited>
			<subEntries />
		</entry>
		<entry name="018" offset="00" relocatable="true" max_length="0">
			<original />
			<edited />
			<subEntries />
		</entry>
	</entries>
</kup>