<?xml version="1.0" encoding="utf-8"?>
<kup encoding="utf-16" ramOffset="00" optimizeStrings="true">
	<pointerTables />
	<stringBounds />
	<entries>
		<entry name="001" offset="00" relocatable="true" max_length="0">
			<original>&#xE;&#x3; &#x0;Hello ! &#xE;&#x7;&#x0;&#x4;&#x10;&#x0;&#x0;&#x0;&#xE;&#x3;&#x17;&#x0;Serais-tu un&#xE;&#xE;&#x6;&#x6;&#x0;&#x0;&#x2;&#x0;e&#x0; de mes
voisin&#xE;&#xE;&#x6;
&#x2;&#x0;s&#x0;&#x4;&#x0;e&#x0;s&#x0; ?&#xE;&#x0;&#x4;&#x0;&#xE;&#x3;&#x10;&#x0;Oh, &#xE;&#x7;&#x0;&#x4;&#x8;&#x0;&#x0;&#x0;alors ce serait toi, &#xE;&#x5;&#x8;&#x0; ?&#xE;&#x7;&#x0;&#x4;&#x1E;&#x0;&#x0;&#x0;
J'ai entendu beaucoup de bien sur
ton compte, tu sais, &#xE;&#x5;&#x7;&#x0;.
&#xE;&#x3;'&#x0;Je suis ravie de faire ta rencontre.&#xE;&#x7;&#x0;&#x4;&#x19;&#x0;&#x0;&#x0;
Mon nom est &#xE;&#x5;&#x1;&#x0;. &#xE;&#x7;&#x0;&#x4;&#x19;&#x0;&#x0;&#x0;J'ai quitté
&#xE;&#x11;&#x2;&#x2;&#x0;&#x0; pour venir m'installer ici.
&#xE;&#x3;%&#x0;Pour l'instant, &#xE;&#x7;&#x0;&#x4;&#x8;&#x0;&#x0;&#x0;j'en suis encore à
défaire mes valises, &#xE;&#x7;&#x0;&#x4;&#xC;&#x0;&#x0;&#x0;mais demain je
pourrai enfin visiter un peu la ville.
&#xE;&#x3;&#x1;&#x0;Peut-être aurai-je la chance de te
croiser au détour d'un chemin ?</original>
			<edited>&#xE;&#x3; &#x0;Hello ! &#xE;&#x7;&#x0;&#x4;&#x10;&#x0;&#x0;&#x0;&#xE;&#x3;&#x17;&#x0;Serais-tu un&#xE;&#xE;&#x6;&#x6;&#x0;&#x0;&#x2;&#x0;e&#x0; de mes
voisin&#xE;&#xE;&#x6;
&#x2;&#x0;s&#x0;&#x4;&#x0;e&#x0;s&#x0; ?&#xE;&#x0;&#x4;&#x0;&#xE;&#x3;&#x10;&#x0;Oh, &#xE;&#x7;&#x0;&#x4;&#x8;&#x0;&#x0;&#x0;alors ce serait toi, &#xE;&#x5;&#x8;&#x0; ?&#xE;&#x7;&#x0;&#x4;&#x1E;&#x0;&#x0;&#x0;
J'ai entendu beaucoup de bien sur
ton compte, tu sais, &#xE;&#x5;&#x7;&#x0;.
&#xE;&#x3;'&#x0;Je suis ravie de faire ta rencontre.&#xE;&#x7;&#x0;&#x4;&#x19;&#x0;&#x0;&#x0;
Mon nom est &#xE;&#x5;&#x1;&#x0;. &#xE;&#x7;&#x0;&#x4;&#x19;&#x0;&#x0;&#x0;J'ai quitté
&#xE;&#x11;&#x2;&#x2;&#x0;&#x0; pour venir m'installer ici.
&#xE;&#x3;%&#x0;Pour l'instant, &#xE;&#x7;&#x0;&#x4;&#x8;&#x0;&#x0;&#x0;j'en suis encore à
défaire mes valises, &#xE;&#x7;&#x0;&#x4;&#xC;&#x0;&#x0;&#x0;mais demain je
pourrai enfin visiter un peu la ville.
&#xE;&#x3;&#x1;&#x0;Peut-être aurai-je la chance de te
croiser au détour d'un chemin ?</edited>
			<subEntries />
		</entry>
		<entry name="002" offset="00" relocatable="true" max_length="0">
			<original>&#xE;&#x3;	&#x0;Ho&#xE;&#x7;&#x0;&#x4;&#x8;&#x0;&#x0;&#x0;.&#xE;&#x7;&#x0;&#x4;&#x8;&#x0;&#x0;&#x0;.&#xE;&#x7;&#x0;&#x4;&#x8;&#x0;&#x0;&#x0;.&#xE;&#x7;&#x0;&#x4;&#x8;&#x0;&#x0;&#x0; C'est gentil de me souhaiter la
bienvenue,&#xE;&#x7;&#x0;&#x4;&#x8;&#x0;&#x0;&#x0; mais je ne peux pas te
recevoir dans ces conditions&#xE;&#x7;&#x0;&#x4;&#x8;&#x0;&#x0;&#x0;.&#xE;&#x7;&#x0;&#x4;&#x8;&#x0;&#x0;&#x0;.&#xE;&#x7;&#x0;&#x4;&#x8;&#x0;&#x0;&#x0;.&#xE;&#x7;&#x0;&#x4;&#x8;&#x0;&#x0;&#x0;
Quel est ton nom ?&#xE;&#x7;&#x0;&#x4;&#x1E;&#x0;&#x0;&#x0; &#xE;&#xE;&#x3;&#x0;&#xE;&#x5;&#x8;&#x0; ?&#xE;&#x7;&#x0;&#x4;&#x1E;&#x0;&#x0;&#x0;
&#xE;&#x3; &#x0;Enchantée, &#xE;&#x5;&#x8;&#x0;.&#xE;&#x7;&#x0;&#x4;&#x1E;&#x0;&#x0;&#x0; Je suis
&#xE;&#x5;&#x1;&#x0;. &#xE;&#x7;&#x0;&#x4;&#x14;&#x0;&#x0;&#x0;Je viens &#xE;&#xE;
&#xE;&#x6;&#x0;d&#x0;e&#x0; &#x0;&#x4;&#x0;d&#x0;'&#x0;&#xE;&#x11;&#x2;&#x2;&#x0;&#x0;.
&#xE;&#x3;&#x1B;&#x0;Oh, &#xE;&#x7;&#x0;&#x4;&#x10;&#x0;&#x0;&#x0;vraiment,&#xE;&#x7;&#x0;&#x4;&#x10;&#x0;&#x0;&#x0; je suis toute honteuse
de te recevoir au milieu d'un tel
désordre...
&#xE;&#x3;'&#x0;Repasse plutôt demain, veux-tu ?&#xE;&#x7;&#x0;&#x4;&#x1E;&#x0;&#x0;&#x0;
D'ici là j'aurai nettoyé la maison.</original>
			<edited>&#xE;&#x3;	&#x0;Ho&#xE;&#x7;&#x0;&#x4;&#x8;&#x0;&#x0;&#x0;.&#xE;&#x7;&#x0;&#x4;&#x8;&#x0;&#x0;&#x0;.&#xE;&#x7;&#x0;&#x4;&#x8;&#x0;&#x0;&#x0;.&#xE;&#x7;&#x0;&#x4;&#x8;&#x0;&#x0;&#x0; C'est gentil de me souhaiter la
bienvenue,&#xE;&#x7;&#x0;&#x4;&#x8;&#x0;&#x0;&#x0; mais je ne peux pas te
recevoir dans ces conditions&#xE;&#x7;&#x0;&#x4;&#x8;&#x0;&#x0;&#x0;.&#xE;&#x7;&#x0;&#x4;&#x8;&#x0;&#x0;&#x0;.&#xE;&#x7;&#x0;&#x4;&#x8;&#x0;&#x0;&#x0;.&#xE;&#x7;&#x0;&#x4;&#x8;&#x0;&#x0;&#x0;
Quel est ton nom ?&#xE;&#x7;&#x0;&#x4;&#x1E;&#x0;&#x0;&#x0; &#xE;&#xE;&#x3;&#x0;&#xE;&#x5;&#x8;&#x0; ?&#xE;&#x7;&#x0;&#x4;&#x1E;&#x0;&#x0;&#x0;
&#xE;&#x3; &#x0;Enchantée, &#xE;&#x5;&#x8;&#x0;.&#xE;&#x7;&#x0;&#x4;&#x1E;&#x0;&#x0;&#x0; Je suis
&#xE;&#x5;&#x1;&#x0;. &#xE;&#x7;&#x0;&#x4;&#x14;&#x0;&#x0;&#x0;Je viens &#xE;&#xE;
&#xE;&#x6;&#x0;d&#x0;e&#x0; &#x0;&#x4;&#x0;d&#x0;'&#x0;&#xE;&#x11;&#x2;&#x2;&#x0;&#x0;.
&#xE;&#x3;&#x1B;&#x0;Oh, &#xE;&#x7;&#x0;&#x4;&#x10;&#x0;&#x0;&#x0;vraiment,&#xE;&#x7;&#x0;&#x4;&#x10;&#x0;&#x0;&#x0; je suis toute honteuse
de te recevoir au milieu d'un tel
désordre...
&#xE;&#x3;'&#x0;Repasse plutôt demain, veux-tu ?&#xE;&#x7;&#x0;&#x4;&#x1E;&#x0;&#x0;&#x0;
D'ici là j'aurai nettoyé la maison.</edited>
			<subEntries />
		</entry>
		<entry name="003" offset="00" relocatable="true" max_length="0">
			<original>&#xE;&#x3;&#x12;&#x0;Ho !&#xE;&#x7;&#x0;&#x4;&#x14;&#x0;&#x0;&#x0; Que viens-tu faire chez moi ?&#xE;&#x7;&#x0;&#x4;&#x1E;&#x0;&#x0;&#x0;
Tu viens me souhaiter la bienvenue
en ville ?&#xE;&#x7;&#x0;&#x4;&#x14;&#x0;&#x0;&#x0; &#xE;&#x3;&#x1;&#x0;Comme c'est gentil !
&#xE;&#x3;	&#x0;Comme tu le vois, je n'ai pas fini de
défaire mes valises, &#xE;&#x7;&#x0;&#x4;&#x8;&#x0;&#x0;&#x0;et j'avoue que
cet emménagement m'a exténuée...
&#xE;&#x3; &#x0;Je me nomme &#xE;&#x5;&#x1;&#x0;,&#xE;&#x7;&#x0;&#x4;&#x8;&#x0;&#x0;&#x0;
et je suis originaire &#xE;&#xE;
&#xE;&#x6;&#x0;d&#x0;e&#x0; &#x0;&#x4;&#x0;d&#x0;'&#x0;&#xE;&#x11;&#x2;&#x2;&#x0;&#x0;.
&#xE;&#x3;&#x17;&#x0;Quel est ton nom ?&#xE;&#x7;&#x1;&#x0; &#xE;&#xE;&#x3;&#x0;&#xE;&#x5;&#x0;&#x0; ?&#xE;&#x7;&#x0;&#x4;&#x10;&#x0;&#x0;&#x0;
Ravie de faire ta connaissance&#xE;&#x7;&#x0;&#x4;&#x8;&#x0;&#x0;&#x0;,
&#xE;&#x5;&#x0;&#x0;.&#xE;&#x0;&#x4;&#x0;&#xE;&#x3;&#x16;&#x0;Reviens plutôt me voir demain,
veux-tu ? Nous serons plus à l'aise
pour discuter, &#xE;&#x5;&#x7;&#x0;.</original>
			<edited>&#xE;&#x3;&#x12;&#x0;Ho !&#xE;&#x7;&#x0;&#x4;&#x14;&#x0;&#x0;&#x0; Que viens-tu faire chez moi ?&#xE;&#x7;&#x0;&#x4;&#x1E;&#x0;&#x0;&#x0;
Tu viens me souhaiter la bienvenue
en ville ?&#xE;&#x7;&#x0;&#x4;&#x14;&#x0;&#x0;&#x0; &#xE;&#x3;&#x1;&#x0;Comme c'est gentil !
&#xE;&#x3;	&#x0;Comme tu le vois, je n'ai pas fini de
défaire mes valises, &#xE;&#x7;&#x0;&#x4;&#x8;&#x0;&#x0;&#x0;et j'avoue que
cet emménagement m'a exténuée...
&#xE;&#x3; &#x0;Je me nomme &#xE;&#x5;&#x1;&#x0;,&#xE;&#x7;&#x0;&#x4;&#x8;&#x0;&#x0;&#x0;
et je suis originaire &#xE;&#xE;
&#xE;&#x6;&#x0;d&#x0;e&#x0; &#x0;&#x4;&#x0;d&#x0;'&#x0;&#xE;&#x11;&#x2;&#x2;&#x0;&#x0;.
&#xE;&#x3;&#x17;&#x0;Quel est ton nom ?&#xE;&#x7;&#x1;&#x0; &#xE;&#xE;&#x3;&#x0;&#xE;&#x5;&#x0;&#x0; ?&#xE;&#x7;&#x0;&#x4;&#x10;&#x0;&#x0;&#x0;
Ravie de faire ta connaissance&#xE;&#x7;&#x0;&#x4;&#x8;&#x0;&#x0;&#x0;,
&#xE;&#x5;&#x0;&#x0;.&#xE;&#x0;&#x4;&#x0;&#xE;&#x3;&#x16;&#x0;Reviens plutôt me voir demain,
veux-tu ? Nous serons plus à l'aise
pour discuter, &#xE;&#x5;&#x7;&#x0;.</edited>
			<subEntries />
		</entry>
		<entry name="004" offset="00" relocatable="true" max_length="0">
			<original>&#xE;&#x3;&#xB;&#x0;Hmmm&#xE;&#x7;&#x0;&#x4;&#x8;&#x0;&#x0;&#x0;.&#xE;&#x7;&#x0;&#x4;&#x8;&#x0;&#x0;&#x0;.&#xE;&#x7;&#x0;&#x4;&#x8;&#x0;&#x0;&#x0;.&#xE;&#x7;&#x0;&#x4;&#x8;&#x0;&#x0;&#x0; Nous nous sommes déjà
rencontré&#xE;&#xE;&#x6;
&#x2;&#x0;s&#x0;&#x4;&#x0;e&#x0;s&#x0;, je crois&#xE;&#x7;&#x0;&#x4;&#x8;&#x0;&#x0;&#x0;.&#xE;&#x7;&#x0;&#x4;&#x8;&#x0;&#x0;&#x0;.&#xE;&#x7;&#x0;&#x4;&#x8;&#x0;&#x0;&#x0;.&#xE;&#x7;&#x0;&#x4;&#x8;&#x0;&#x0;&#x0; &#xE;&#x3;	&#x0;mais je ne
suis plus très sûre de ton nom...
&#xE;&#x3;&#x10;&#x0;Ah, oui !&#xE;&#x7;&#x0;&#x4;&#x14;&#x0;&#x0;&#x0; &#xE;&#xE;&#x3;&#x0;&#xE;&#x5;&#x8;&#x0; !&#xE;&#x7;&#x0;&#x4;&#x14;&#x0;&#x0;&#x0; Voilà, &#xE;&#x7;&#x0;&#x4;&#x10;&#x0;&#x0;&#x0;ça me
revient ! &#xE;&#x7;&#x0;&#x4;&#x1E;&#x0;&#x0;&#x0;&#xE;&#x3;&#x1;&#x0;Te souviens-tu du mien ?&#xE;&#x7;&#x0;&#x4;&#x1E;&#x0;&#x0;&#x0;
&#xE;&#x5;&#x1;&#x0;,&#xE;&#x7;&#x0;&#x4;&#x14;&#x0;&#x0;&#x0; j'habitais à &#xE;&#x11;&#x2;&#x2;&#x0;&#x0;.
&#xE;&#x3;&amp;&#x0;J'ai entendu beaucoup de bien sur
ton compte, tu sais.</original>
			<edited>&#xE;&#x3;&#xB;&#x0;Hmmm&#xE;&#x7;&#x0;&#x4;&#x8;&#x0;&#x0;&#x0;.&#xE;&#x7;&#x0;&#x4;&#x8;&#x0;&#x0;&#x0;.&#xE;&#x7;&#x0;&#x4;&#x8;&#x0;&#x0;&#x0;.&#xE;&#x7;&#x0;&#x4;&#x8;&#x0;&#x0;&#x0; Nous nous sommes déjà
rencontré&#xE;&#xE;&#x6;
&#x2;&#x0;s&#x0;&#x4;&#x0;e&#x0;s&#x0;, je crois&#xE;&#x7;&#x0;&#x4;&#x8;&#x0;&#x0;&#x0;.&#xE;&#x7;&#x0;&#x4;&#x8;&#x0;&#x0;&#x0;.&#xE;&#x7;&#x0;&#x4;&#x8;&#x0;&#x0;&#x0;.&#xE;&#x7;&#x0;&#x4;&#x8;&#x0;&#x0;&#x0; &#xE;&#x3;	&#x0;mais je ne
suis plus très sûre de ton nom...
&#xE;&#x3;&#x10;&#x0;Ah, oui !&#xE;&#x7;&#x0;&#x4;&#x14;&#x0;&#x0;&#x0; &#xE;&#xE;&#x3;&#x0;&#xE;&#x5;&#x8;&#x0; !&#xE;&#x7;&#x0;&#x4;&#x14;&#x0;&#x0;&#x0; Voilà, &#xE;&#x7;&#x0;&#x4;&#x10;&#x0;&#x0;&#x0;ça me
revient ! &#xE;&#x7;&#x0;&#x4;&#x1E;&#x0;&#x0;&#x0;&#xE;&#x3;&#x1;&#x0;Te souviens-tu du mien ?&#xE;&#x7;&#x0;&#x4;&#x1E;&#x0;&#x0;&#x0;
&#xE;&#x5;&#x1;&#x0;,&#xE;&#x7;&#x0;&#x4;&#x14;&#x0;&#x0;&#x0; j'habitais à &#xE;&#x11;&#x2;&#x2;&#x0;&#x0;.
&#xE;&#x3;&amp;&#x0;J'ai entendu beaucoup de bien sur
ton compte, tu sais.</edited>
			<subEntries />
		</entry>
		<entry name="005" offset="00" relocatable="true" max_length="0">
			<original>&#xE;&#x3;&#x10;&#x0;Tu es &#xE;&#xE;
&#xE;&#x6;&#x0;d&#x0;e&#x0; &#x0;&#x4;&#x0;d&#x0;'&#x0;&#xE;&#x5;&#x5;&#x0;, j'imagine ?&#xE;&#x7;&#x0;&#x4;&#x1E;&#x0;&#x0;&#x0; Oh,&#xE;&#x7;&#x0;&#x4;&#x8;&#x0;&#x0;&#x0;
c'est toi &#xE;&#x5;&#x8;&#x0; ? &#xE;&#x7;&#x0;&#x4;&#x14;&#x0;&#x0;&#x0;J'ai beaucoup
entendu parler de toi, tu sais.
&#xE;&#x3; &#x0;Je me nomme &#xE;&#x5;&#x1;&#x0;.&#xE;&#x7;&#x0;&#x4;&#x1E;&#x0;&#x0;&#x0; J'ai
quitté &#xE;&#x11;&#x2;&#x2;&#x0;&#x0; pour venir
m'installer ici, &#xE;&#x5;&#x7;&#x0;.
&#xE;&#x3;&#xB;&#x0;J'espère que je ne me ferai pas
chasser cette fois&#xE;&#x7;&#x0;&#x4;&#x8;&#x0;&#x0;&#x0;.&#xE;&#x7;&#x0;&#x4;&#x8;&#x0;&#x0;&#x0;.&#xE;&#x7;&#x0;&#x4;&#x8;&#x0;&#x0;&#x0;.&#xE;&#x0;&#x4;&#x0;&#xE;&#x3;&#xD;&#x0;Oh ! &#xE;&#x7;&#x0;&#x4;&#x8;&#x0;&#x0;&#x0;Euh&#xE;&#x7;&#x0;&#x4;&#x8;&#x0;&#x0;&#x0;.&#xE;&#x7;&#x0;&#x4;&#x8;&#x0;&#x0;&#x0;.&#xE;&#x7;&#x0;&#x4;&#x8;&#x0;&#x0;&#x0;.&#xE;&#x7;&#x0;&#x4;&#x8;&#x0;&#x0;&#x0; Je veux dire,&#xE;&#x7;&#x0;&#x4;&#x10;&#x0;&#x0;&#x0; j'espère
qu'il y a beaucoup d'insectes à
chasser dans cette ville !</original>
			<edited>&#xE;&#x3;&#x10;&#x0;Tu es &#xE;&#xE;
&#xE;&#x6;&#x0;d&#x0;e&#x0; &#x0;&#x4;&#x0;d&#x0;'&#x0;&#xE;&#x5;&#x5;&#x0;, j'imagine ?&#xE;&#x7;&#x0;&#x4;&#x1E;&#x0;&#x0;&#x0; Oh,&#xE;&#x7;&#x0;&#x4;&#x8;&#x0;&#x0;&#x0;
c'est toi &#xE;&#x5;&#x8;&#x0; ? &#xE;&#x7;&#x0;&#x4;&#x14;&#x0;&#x0;&#x0;J'ai beaucoup
entendu parler de toi, tu sais.
&#xE;&#x3; &#x0;Je me nomme &#xE;&#x5;&#x1;&#x0;.&#xE;&#x7;&#x0;&#x4;&#x1E;&#x0;&#x0;&#x0; J'ai
quitté &#xE;&#x11;&#x2;&#x2;&#x0;&#x0; pour venir
m'installer ici, &#xE;&#x5;&#x7;&#x0;.
&#xE;&#x3;&#xB;&#x0;J'espère que je ne me ferai pas
chasser cette fois&#xE;&#x7;&#x0;&#x4;&#x8;&#x0;&#x0;&#x0;.&#xE;&#x7;&#x0;&#x4;&#x8;&#x0;&#x0;&#x0;.&#xE;&#x7;&#x0;&#x4;&#x8;&#x0;&#x0;&#x0;.&#xE;&#x0;&#x4;&#x0;&#xE;&#x3;&#xD;&#x0;Oh ! &#xE;&#x7;&#x0;&#x4;&#x8;&#x0;&#x0;&#x0;Euh&#xE;&#x7;&#x0;&#x4;&#x8;&#x0;&#x0;&#x0;.&#xE;&#x7;&#x0;&#x4;&#x8;&#x0;&#x0;&#x0;.&#xE;&#x7;&#x0;&#x4;&#x8;&#x0;&#x0;&#x0;.&#xE;&#x7;&#x0;&#x4;&#x8;&#x0;&#x0;&#x0; Je veux dire,&#xE;&#x7;&#x0;&#x4;&#x10;&#x0;&#x0;&#x0; j'espère
qu'il y a beaucoup d'insectes à
chasser dans cette ville !</edited>
			<subEntries />
		</entry>
		<entry name="006" offset="00" relocatable="true" max_length="0">
			<original>&#xE;&#x3;&#x10;&#x0;Tu es &#xE;&#xE;
&#xE;&#x6;&#x0;d&#x0;e&#x0; &#x0;&#x4;&#x0;d&#x0;'&#x0;&#xE;&#x5;&#x5;&#x0;, n'est-ce pas ?&#xE;&#x7;&#x0;&#x4;&#x1E;&#x0;&#x0;&#x0;
Oh,&#xE;&#x7;&#x0;&#x4;&#x8;&#x0;&#x0;&#x0; c'est donc toi &#xE;&#x5;&#x8;&#x0; ? &#xE;&#x7;&#x0;&#x4;&#x14;&#x0;&#x0;&#x0;J'ai
entendu beaucoup de bien sur toi.
&#xE;&#x3; &#x0;Je me nomme &#xE;&#x5;&#x1;&#x0;.&#xE;&#x7;&#x0;&#x4;&#x1E;&#x0;&#x0;&#x0; Avant, je
vivais à &#xE;&#x11;&#x2;&#x2;&#x0;&#x0;, mais je préfère
nettement &#xE;&#x5;&#x5;&#x0;.
&#xE;&#x3;&#xB;&#x0;Je parie que je peux deviner quel
est ton plat favori&#xE;&#x7;&#x0;&#x4;&#x8;&#x0;&#x0;&#x0;.&#xE;&#x7;&#x0;&#x4;&#x8;&#x0;&#x0;&#x0;.&#xE;&#x7;&#x0;&#x4;&#x8;&#x0;&#x0;&#x0;.&#xE;&#x7;&#x0;&#x4;&#x8;&#x0;&#x0;&#x0;
&#xE;&#xE;&#x1;&#x0;&#xE;&#x5;&#x13;&#x2;&#x0;&#x0;. Exact ?
Et je suis sûre que comme moi, tu
aimes &#xE;&#x5;&#x12;&#x2;&#x0;&#x0;. &#xE;&#x7;&#x0;&#x4;&#x10;&#x0;&#x0;&#x0;Je me
trompe ?
&#xE;&#x3;#&#x0;Magnifique ! &#xE;&#x7;&#x0;&#x4;&#x8;&#x0;&#x0;&#x0;Je suis certaine que toi
et moi allons devenir de grand&#xE;&#xE;&#x6;
&#x2;&#x0;s&#x0;&#x4;&#x0;e&#x0;s&#x0;
ami&#xE;&#xE;&#x6;
&#x2;&#x0;s&#x0;&#x4;&#x0;e&#x0;s&#x0;, &#xE;&#x5;&#x7;&#x0; !</original>
			<edited>&#xE;&#x3;&#x10;&#x0;Tu es &#xE;&#xE;
&#xE;&#x6;&#x0;d&#x0;e&#x0; &#x0;&#x4;&#x0;d&#x0;'&#x0;&#xE;&#x5;&#x5;&#x0;, n'est-ce pas ?&#xE;&#x7;&#x0;&#x4;&#x1E;&#x0;&#x0;&#x0;
Oh,&#xE;&#x7;&#x0;&#x4;&#x8;&#x0;&#x0;&#x0; c'est donc toi &#xE;&#x5;&#x8;&#x0; ? &#xE;&#x7;&#x0;&#x4;&#x14;&#x0;&#x0;&#x0;J'ai
entendu beaucoup de bien sur toi.
&#xE;&#x3; &#x0;Je me nomme &#xE;&#x5;&#x1;&#x0;.&#xE;&#x7;&#x0;&#x4;&#x1E;&#x0;&#x0;&#x0; Avant, je
vivais à &#xE;&#x11;&#x2;&#x2;&#x0;&#x0;, mais je préfère
nettement &#xE;&#x5;&#x5;&#x0;.
&#xE;&#x3;&#xB;&#x0;Je parie que je peux deviner quel
est ton plat favori&#xE;&#x7;&#x0;&#x4;&#x8;&#x0;&#x0;&#x0;.&#xE;&#x7;&#x0;&#x4;&#x8;&#x0;&#x0;&#x0;.&#xE;&#x7;&#x0;&#x4;&#x8;&#x0;&#x0;&#x0;.&#xE;&#x7;&#x0;&#x4;&#x8;&#x0;&#x0;&#x0;
&#xE;&#xE;&#x1;&#x0;&#xE;&#x5;&#x13;&#x2;&#x0;&#x0;. Exact ?
Et je suis sûre que comme moi, tu
aimes &#xE;&#x5;&#x12;&#x2;&#x0;&#x0;. &#xE;&#x7;&#x0;&#x4;&#x10;&#x0;&#x0;&#x0;Je me
trompe ?
&#xE;&#x3;#&#x0;Magnifique ! &#xE;&#x7;&#x0;&#x4;&#x8;&#x0;&#x0;&#x0;Je suis certaine que toi
et moi allons devenir de grand&#xE;&#xE;&#x6;
&#x2;&#x0;s&#x0;&#x4;&#x0;e&#x0;s&#x0;
ami&#xE;&#xE;&#x6;
&#x2;&#x0;s&#x0;&#x4;&#x0;e&#x0;s&#x0;, &#xE;&#x5;&#x7;&#x0; !</edited>
			<subEntries />
		</entry>
		<entry name="007" offset="00" relocatable="true" max_length="0">
			<original>&#xE;&#x3;&#xF;&#x0;Cela fait une semaine que j'ai
emménagé en ville, et nous n'avons
toujours pas été présenté&#xE;&#xE;&#x6;
&#x2;&#x0;s&#x0;&#x4;&#x0;e&#x0;s&#x0;...
&#xE;&#x3; &#x0;Alors je vais le faire moi-même.&#xE;&#x7;&#x0;&#x4;&#x10;&#x0;&#x0;&#x0; Je
me nomme &#xE;&#x5;&#x1;&#x0;. &#xE;&#x7;&#x0;&#x4;&#x10;&#x0;&#x0;&#x0;Et toi ?&#xE;&#x7;&#x1;&#x0;
&#xE;&#xE;&#x3;&#x0;&#xE;&#x5;&#x8;&#x0; ?&#xE;&#x7;&#x0;&#x4;&#x14;&#x0;&#x0;&#x0; &#xE;&#x3;&amp;&#x0;Quel beau nom !
&#xE;&#x3;&#x1D;&#x0;J'ai comme le sentiment que toi et
moi allons devenir de vrai&#xE;&#xE;&#x6; &#xC;&#x0;s&#x0; &#x0;a&#x0;m&#x0;i&#x0;s&#x0;&#x10;&#x0;e&#x0;s&#x0; &#x0;a&#x0;m&#x0;i&#x0;e&#x0;s&#x0; !</original>
			<edited>&#xE;&#x3;&#xF;&#x0;Cela fait une semaine que j'ai
emménagé en ville, et nous n'avons
toujours pas été présenté&#xE;&#xE;&#x6;
&#x2;&#x0;s&#x0;&#x4;&#x0;e&#x0;s&#x0;...
&#xE;&#x3; &#x0;Alors je vais le faire moi-même.&#xE;&#x7;&#x0;&#x4;&#x10;&#x0;&#x0;&#x0; Je
me nomme &#xE;&#x5;&#x1;&#x0;. &#xE;&#x7;&#x0;&#x4;&#x10;&#x0;&#x0;&#x0;Et toi ?&#xE;&#x7;&#x1;&#x0;
&#xE;&#xE;&#x3;&#x0;&#xE;&#x5;&#x8;&#x0; ?&#xE;&#x7;&#x0;&#x4;&#x14;&#x0;&#x0;&#x0; &#xE;&#x3;&amp;&#x0;Quel beau nom !
&#xE;&#x3;&#x1D;&#x0;J'ai comme le sentiment que toi et
moi allons devenir de vrai&#xE;&#xE;&#x6; &#xC;&#x0;s&#x0; &#x0;a&#x0;m&#x0;i&#x0;s&#x0;&#x10;&#x0;e&#x0;s&#x0; &#x0;a&#x0;m&#x0;i&#x0;e&#x0;s&#x0; !</edited>
			<subEntries />
		</entry>
		<entry name="008" offset="00" relocatable="true" max_length="0">
			<original>&#xE;&#x3;&#x10;&#x0;Tu dois être &#xE;&#x5;&#x8;&#x0;. &#xE;&#x7;&#x0;&#x4;&#x1E;&#x0;&#x0;&#x0;Tout le
monde ne parle que de toi, ici...&#xE;&#x0;&#x4;&#x0;&#xE;&#x3;	&#x0;Tu ne dois pas sortir souvent,&#xE;&#x7;&#x0;&#x4;&#x8;&#x0;&#x0;&#x0; car
c'est la première fois que je te vois
depuis que j'ai emménagé...
&#xE;&#x3; &#x0;Je m'appelle &#xE;&#x5;&#x1;&#x0;. &#xE;&#x7;&#x0;&#x4;&#x14;&#x0;&#x0;&#x0;Enchantée.&#xE;&#x7;&#x0;&#x4;&#x1E;&#x0;&#x0;&#x0;
&#xE;&#x3;$&#x0;Tu as sans doute entendu parler de
moi aussi, non ?
&#xE;&#x3;&#x1;&#x0;Je suis ravie d'avoir fait ta
connaissance. J'espère te revoir
bientôt, &#xE;&#x5;&#x7;&#x0;.</original>
			<edited>&#xE;&#x3;&#x10;&#x0;Tu dois être &#xE;&#x5;&#x8;&#x0;. &#xE;&#x7;&#x0;&#x4;&#x1E;&#x0;&#x0;&#x0;Tout le
monde ne parle que de toi, ici...&#xE;&#x0;&#x4;&#x0;&#xE;&#x3;	&#x0;Tu ne dois pas sortir souvent,&#xE;&#x7;&#x0;&#x4;&#x8;&#x0;&#x0;&#x0; car
c'est la première fois que je te vois
depuis que j'ai emménagé...
&#xE;&#x3; &#x0;Je m'appelle &#xE;&#x5;&#x1;&#x0;. &#xE;&#x7;&#x0;&#x4;&#x14;&#x0;&#x0;&#x0;Enchantée.&#xE;&#x7;&#x0;&#x4;&#x1E;&#x0;&#x0;&#x0;
&#xE;&#x3;$&#x0;Tu as sans doute entendu parler de
moi aussi, non ?
&#xE;&#x3;&#x1;&#x0;Je suis ravie d'avoir fait ta
connaissance. J'espère te revoir
bientôt, &#xE;&#x5;&#x7;&#x0;.</edited>
			<subEntries />
		</entry>
		<entry name="009" offset="00" relocatable="true" max_length="0">
			<original>&#xE;&#x3;&#x10;&#x0;Tu dois être &#xE;&#x5;&#x8;&#x0;. &#xE;&#x7;&#x0;&#x4;&#x1E;&#x0;&#x0;&#x0;Tout le
monde ne parle que de toi, ici...&#xE;&#x0;&#x4;&#x0;&#xE;&#x3;	&#x0;&#xE;&#x7;&#x0;&#x4;&#xC;&#x0;&#x0;&#x0;Tu ne dois pas sortir souvent,&#xE;&#x7;&#x0;&#x4;&#xC;&#x0;&#x0;&#x0; car
c'est la première fois que je te vois.&#xE;&#x7;&#x0;&#x4;&#x1E;&#x0;&#x0;&#x0;
&#xE;&#x3; &#x0;Je m'appelle &#xE;&#x5;&#x1;&#x0;. &#xE;&#x7;&#x0;&#x4;&#x14;&#x0;&#x0;&#x0;Enchantée.&#xE;&#x7;&#x0;&#x4;&#x1E;&#x0;&#x0;&#x0;
&#xE;&#x3;!&#x0;Avant de venir ici, j'habitais
&#xE;&#x11;&#x2;&#x2;&#x0;&#x0;.&#xE;&#x7;&#x0;&#x4;&#x1E;&#x0;&#x0;&#x0; Entre nous, &#xE;&#x7;&#x0;&#x4;&#x10;&#x0;&#x0;&#x0;je trouve la
ville &#xE;&#xE;
&#xE;&#x6;&#x0;d&#x0;e&#x0; &#x0;&#x4;&#x0;d&#x0;'&#x0;&#xE;&#x5;&#x5;&#x0; bien plus jolie.
&#xE;&#x3;&#x1;&#x0;Je suis ravie d'avoir fait ta
connaissance. J'espère te revoir
bientôt, &#xE;&#x5;&#x7;&#x0;.</original>
			<edited>&#xE;&#x3;&#x10;&#x0;Tu dois être &#xE;&#x5;&#x8;&#x0;. &#xE;&#x7;&#x0;&#x4;&#x1E;&#x0;&#x0;&#x0;Tout le
monde ne parle que de toi, ici...&#xE;&#x0;&#x4;&#x0;&#xE;&#x3;	&#x0;&#xE;&#x7;&#x0;&#x4;&#xC;&#x0;&#x0;&#x0;Tu ne dois pas sortir souvent,&#xE;&#x7;&#x0;&#x4;&#xC;&#x0;&#x0;&#x0; car
c'est la première fois que je te vois.&#xE;&#x7;&#x0;&#x4;&#x1E;&#x0;&#x0;&#x0;
&#xE;&#x3; &#x0;Je m'appelle &#xE;&#x5;&#x1;&#x0;. &#xE;&#x7;&#x0;&#x4;&#x14;&#x0;&#x0;&#x0;Enchantée.&#xE;&#x7;&#x0;&#x4;&#x1E;&#x0;&#x0;&#x0;
&#xE;&#x3;!&#x0;Avant de venir ici, j'habitais
&#xE;&#x11;&#x2;&#x2;&#x0;&#x0;.&#xE;&#x7;&#x0;&#x4;&#x1E;&#x0;&#x0;&#x0; Entre nous, &#xE;&#x7;&#x0;&#x4;&#x10;&#x0;&#x0;&#x0;je trouve la
ville &#xE;&#xE;
&#xE;&#x6;&#x0;d&#x0;e&#x0; &#x0;&#x4;&#x0;d&#x0;'&#x0;&#xE;&#x5;&#x5;&#x0; bien plus jolie.
&#xE;&#x3;&#x1;&#x0;Je suis ravie d'avoir fait ta
connaissance. J'espère te revoir
bientôt, &#xE;&#x5;&#x7;&#x0;.</edited>
			<subEntries />
		</entry>
		<entry name="010" offset="00" relocatable="true" max_length="0">
			<original>Ah&#xE;&#x7;&#x0;&#x4;&#x8;&#x0;&#x0;&#x0;.&#xE;&#x7;&#x0;&#x4;&#x8;&#x0;&#x0;&#x0;.&#xE;&#x7;&#x0;&#x4;&#x8;&#x0;&#x0;&#x0;.&#xE;&#x7;&#x0;&#x4;&#x8;&#x0;&#x0;&#x0; ah&#xE;&#x7;&#x0;&#x4;&#x8;&#x0;&#x0;&#x0;.&#xE;&#x7;&#x0;&#x4;&#x8;&#x0;&#x0;&#x0;.&#xE;&#x7;&#x0;&#x4;&#x8;&#x0;&#x0;&#x0;.&#xE;&#x7;&#x0;&#x4;&#x8;&#x0;&#x0;&#x0;&#xE;&#x3;&#x1E;&#x0;&#xE;&#x7;&#xB;&#x0; ATCHOOOUUUM !&#xE;&#x7;&#x0;&#x4; &#x0;&#x0;&#x0;
&#xE;&#x3;&#x19;&#x0;Désolée,&#xE;&#x7;&#x0;&#x4;&#x8;&#x0;&#x0;&#x0; &#xE;&#x7;&#x0;&#x4;&#x10;&#x0;&#x0;&#x0;je suis un peu enrhumée...&#xE;&#x0;&#x4;&#x0;&#xE;&#x3;(&#x0;Il vaut mieux que j'évite de
t'embrasser, &#xE;&#x7;&#x0;&#x4;&#x10;&#x0;&#x0;&#x0;mais le cœur y est.&#xE;&#x7;&#x0;&#x4; &#x0;&#x0;&#x0;
&#xE;&#x3;&#x1;&#x0;Mon nom est &#xE;&#x5;&#x1;&#x0;.&#xE;&#x7;&#x0;&#x4;&#x19;&#x0;&#x0;&#x0; Et toi ?
&#xE;&#x3;&#x19;&#x0;&#xE;&#xE;&#x3;&#x0;&#xE;&#x5;&#x8;&#x0; ?&#xE;&#x7;&#x0;&#x4;&#x10;&#x0;&#x0;&#x0; &#xE;&#x3; &#x0;Enchantée,
&#xE;&#x7;&#x0;&#x4;&#x8;&#x0;&#x0;&#x0;&#xE;&#x5;&#x8;&#x0;.&#xE;&#x7;&#x0;&#x4; &#x0;&#x0;&#x0; Nous parlerons quand
j'irai mieux, &#xE;&#x7;&#x0;&#x4;&#x8;&#x0;&#x0;&#x0;d'accord ?</original>
			<edited>Ah&#xE;&#x7;&#x0;&#x4;&#x8;&#x0;&#x0;&#x0;.&#xE;&#x7;&#x0;&#x4;&#x8;&#x0;&#x0;&#x0;.&#xE;&#x7;&#x0;&#x4;&#x8;&#x0;&#x0;&#x0;.&#xE;&#x7;&#x0;&#x4;&#x8;&#x0;&#x0;&#x0; ah&#xE;&#x7;&#x0;&#x4;&#x8;&#x0;&#x0;&#x0;.&#xE;&#x7;&#x0;&#x4;&#x8;&#x0;&#x0;&#x0;.&#xE;&#x7;&#x0;&#x4;&#x8;&#x0;&#x0;&#x0;.&#xE;&#x7;&#x0;&#x4;&#x8;&#x0;&#x0;&#x0;&#xE;&#x3;&#x1E;&#x0;&#xE;&#x7;&#xB;&#x0; ATCHOOOUUUM !&#xE;&#x7;&#x0;&#x4; &#x0;&#x0;&#x0;
&#xE;&#x3;&#x19;&#x0;Désolée,&#xE;&#x7;&#x0;&#x4;&#x8;&#x0;&#x0;&#x0; &#xE;&#x7;&#x0;&#x4;&#x10;&#x0;&#x0;&#x0;je suis un peu enrhumée...&#xE;&#x0;&#x4;&#x0;&#xE;&#x3;(&#x0;Il vaut mieux que j'évite de
t'embrasser, &#xE;&#x7;&#x0;&#x4;&#x10;&#x0;&#x0;&#x0;mais le cœur y est.&#xE;&#x7;&#x0;&#x4; &#x0;&#x0;&#x0;
&#xE;&#x3;&#x1;&#x0;Mon nom est &#xE;&#x5;&#x1;&#x0;.&#xE;&#x7;&#x0;&#x4;&#x19;&#x0;&#x0;&#x0; Et toi ?
&#xE;&#x3;&#x19;&#x0;&#xE;&#xE;&#x3;&#x0;&#xE;&#x5;&#x8;&#x0; ?&#xE;&#x7;&#x0;&#x4;&#x10;&#x0;&#x0;&#x0; &#xE;&#x3; &#x0;Enchantée,
&#xE;&#x7;&#x0;&#x4;&#x8;&#x0;&#x0;&#x0;&#xE;&#x5;&#x8;&#x0;.&#xE;&#x7;&#x0;&#x4; &#x0;&#x0;&#x0; Nous parlerons quand
j'irai mieux, &#xE;&#x7;&#x0;&#x4;&#x8;&#x0;&#x0;&#x0;d'accord ?</edited>
			<subEntries />
		</entry>
	</entries>
</kup>